ibooks.py
ibooks-0.3.data/scripts/ibooks-script.py
ibooks-0.3.data/scripts/ibooks.exe
ibooks-0.3.data/scripts/ibooks.exe.manifest
ibooks-0.3.dist-info/DESCRIPTION.rst
ibooks-0.3.dist-info/entry_points.txt
ibooks-0.3.dist-info/METADATA
ibooks-0.3.dist-info/pydist.json
ibooks-0.3.dist-info/RECORD
ibooks-0.3.dist-info/top_level.txt
ibooks-0.3.dist-info/WHEEL
