Metadata-Version: 2.0
Name: ibooks
Version: 0.3
Summary: iBooks Author cover and metadata extraction
Home-page: http://github.com/titusz/ibooks/
Author: titusz
Author-email: tp@py7.de
License: BSD
Keywords: ibooks author metadata cover extraction epub epub3
Platform: UNKNOWN
Classifier: Development Status :: 4 - Beta
Classifier: Intended Audience :: Developers
Classifier: Intended Audience :: System Administrators
Classifier: License :: OSI Approved :: BSD License
Classifier: Operating System :: OS Independent
Classifier: Programming Language :: Python
Classifier: Programming Language :: Python :: 2.7
Classifier: Topic :: Desktop Environment :: File Managers
Classifier: Topic :: System :: Filesystems
Classifier: Topic :: Software Development :: Libraries :: Python Modules
Classifier: Topic :: Utilities
